rareeventestimation/__init__.py
rareeventestimation/enkf/EnKF_rare_events.py
rareeventestimation/era/CEIS_GM.py
rareeventestimation/era/CEIS_vMFNM.py
rareeventestimation/era/EMGM.py
rareeventestimation/era/EMvMFNM.py
rareeventestimation/era/ERADist.py
rareeventestimation/era/ERANataf.py
rareeventestimation/era/MCMC.py
rareeventestimation/evaluation/constants.py
rareeventestimation/evaluation/convergence_analysis.py
rareeventestimation/evaluation/visualization.py
rareeventestimation/mixturemodel.py
rareeventestimation/mls2mc/SIS_VMFNM.py
rareeventestimation/problem/diffusion.py
rareeventestimation/problem/flowrate_problem.py
rareeventestimation/problem/problem.py
rareeventestimation/problem/toy_problems.py
rareeventestimation/sis/SIS_GM.py
rareeventestimation/sis/SIS_aCS.py
rareeventestimation/solution.py
rareeventestimation/solver.py
rareeventestimation/utilities.py
rareeventestimation-0.3.0.dist-info/LICENSE
rareeventestimation-0.3.0.dist-info/METADATA
rareeventestimation-0.3.0.dist-info/WHEEL
rareeventestimation-0.3.0.dist-info/RECORD
