Metadata-Version: 2.1
Name: rareeventestimation
Version: 0.3.0
Summary: Estimate rare events with consensus based sampling and other methods.
Home-page: https://pypi.org/project/rareeventestimation/
License: MIT
Author: Konstantin Althaus
Author-email: althaus.konstantin.95@gmail.com
Requires-Python: >=3.8
Classifier: License :: OSI Approved :: MIT License
Classifier: Programming Language :: Python :: 3
Classifier: Programming Language :: Python :: 3.8
Classifier: Programming Language :: Python :: 3.9
Classifier: Programming Language :: Python :: 3.10
Classifier: Programming Language :: Python :: 3.11
Classifier: Programming Language :: Python :: 3.12
Requires-Dist: Pillow (>=9.1.1)
Requires-Dist: argparse (>=1.4.0)
Requires-Dist: ipython (>=8.4.0)
Requires-Dist: jupyter-core (>=4.11.2)
Requires-Dist: matplotlib (>=3.5.2)
Requires-Dist: nbconvert (>=6.5.0)
Requires-Dist: notebook (>=6.4.12)
Requires-Dist: numpy (>=1.22.3)
Requires-Dist: pandas (>=1.4.2)
Requires-Dist: plotly (>=5.8.0)
Requires-Dist: prettytable (>=3.3.0)
Requires-Dist: pytest (>=7.2.0)
Requires-Dist: scikit-fem (>=7.0.1)
Requires-Dist: scipy (>=1.8.1)
Project-URL: Documentation, https://althauskonstantin.github.io/rareeventestimation/
Project-URL: Repository, https://github.com/AlthausKonstantin/rareeventestimation
